random_interrupt/__init__.py
random_interrupt/main.py
random_interrupt-0.1.2.dist-info/LICENSE
random_interrupt-0.1.2.dist-info/METADATA
random_interrupt-0.1.2.dist-info/WHEEL
random_interrupt-0.1.2.dist-info/entry_points.txt
random_interrupt-0.1.2.dist-info/top_level.txt
random_interrupt-0.1.2.dist-info/RECORD
