Metadata-Version: 2.1
Name: random-interrupt
Version: 0.1.2
Summary: A command-line tool that generates random interrupts throughout a specified time period, inspired by Andrew Huberman's research on productivity and focus.
Home-page: https://github.com/gamesh411/random-interrupt
Author: Endre Fülöp
Author-email: gamesh411@gmail.com
Classifier: Development Status :: 3 - Alpha
Classifier: Intended Audience :: Developers
Classifier: License :: OSI Approved :: MIT License
Classifier: Programming Language :: Python :: 3
Classifier: Programming Language :: Python :: 3.10
Requires-Python: >=3.10
License-File: LICENSE
Requires-Dist: plyer ==2.1.0
Provides-Extra: dev
Requires-Dist: pytest ==8.3.3 ; extra == 'dev'
Requires-Dist: pytest-mock ==3.14.0 ; extra == 'dev'
Requires-Dist: pytest-cov ==5.0.0 ; extra == 'dev'
